reactionary/__init__.py
reactionary/conf.py
reactionary/gen_mapping_file.py
reactionary/reactionary.py
reactionary/reactionary_lib.py
reactionary/sphinx-reports-conf.py
reactionary/test_warpath.py
reactionary/validate.py
reactionary/warpath.py
reactionary/dbs/effective-metacyc-orphan-rxns_2020-07-21
reactionary/dbs/metacyc_pwy_metadata.txt
reactionary/dbs/metacyc_pwy_tax-range_rxns.txt
reactionary/dbs/nog2rxn_v4.gz
reactionary/dbs/nog2rxn_v5.gz
reactionary-0.4.1.data/scripts/run-reactionary
reactionary-0.4.1.dist-info/METADATA
reactionary-0.4.1.dist-info/WHEEL
reactionary-0.4.1.dist-info/top_level.txt
reactionary-0.4.1.dist-info/RECORD
