Metadata-Version: 2.1
Name: reactionary
Version: 0.4.1
Summary: Accurately annotate (meta)genomes with MetaCyc reactions.
Home-page: https://bitbucket.org/tomeraltman/reactionary/
Author: Tomer Altman
Author-email: python@me.tomeraltman.net
License: UNKNOWN
Platform: UNKNOWN
Classifier: Programming Language :: Python :: 3
Classifier: License :: OSI Approved :: Mozilla Public License 2.0 (MPL 2.0)
Classifier: Operating System :: POSIX
Requires-Dist: camelot-frs
Requires-Dist: biopython
Requires-Dist: ete3
Requires-Dist: docopt
Requires-Dist: schema
Requires-Dist: future
Requires-Dist: sphinx
Requires-Dist: pypandoc
Requires-Dist: rinohtype
